{"is_source_file": false, "format": null, "description": "", "external_files": [], "external_methods": [], "published": [], "classes": [], "methods": [], "calls": [], "search-terms": [], "state": 2, "file_id": 77, "knowledge_revision": 228, "git_revision": "f81e7268efcf4bf0c1e92ecf1b8f09e164676a23", "hash": "eb383eb5b1dc01e3002a9ef046ef6bf4", "format-version": 4, "code-base-name": "kirana-fintech", "filename": "src/app/globals.css", "revision_history": [{"228": "f81e7268efcf4bf0c1e92ecf1b8f09e164676a23"}]}