{"is_source_file": true, "format": "TypeScript (TSX)", "description": "This file defines a React functional component named Sidebar that manages the display and behavior of a navigation sidebar in a web application. It includes import statements, state management with useState and useEffect hooks, and JSX for rendering UI elements such as logo, navigation items, and footer. It dynamically adjusts layout based on window size and user profile data.", "external_files": ["./SidebarItem", "@/config/sidebar", "react-icons/fa", "lucide-react", "next/link", "@/store/useAuthStore"], "external_methods": ["useState", "useEffect", "setCollapsed", "useAuthStore()"], "published": [], "classes": [], "methods": [{"name": "Sidebar", "description": "Main React component for rendering the sidebar with collapsible behavior based on window size and user profile."}], "calls": ["useState", "useEffect", "setCollapsed", "window.addEventListener", "window.removeEventListener", "profile?.branch?.store?.name", "profile?.branch?.name", "profile?.role", "sidebarMenu.map", "SidebarItem", "useAuthStore()", "Link"], "search-terms": ["Sidebar React component", "TypeScript sidebar layout", "collapsible sidebar", "useAuthStore", "dynamic window resize", "sidebar menu items", "Next.js Link", "React icons", "branch info profile", "navigation toggle button"], "state": 2, "file_id": 33, "knowledge_revision": 194, "git_revision": "407fc76aca9d4e2629877b12781490020c6f85a2", "ctags": [], "hash": "39ca82badc55c2888475e82042f6154e", "format-version": 4, "code-base-name": "kirana-fintech", "filename": "src/components/layout/Sidebar.tsx", "revision_history": [{"194": "407fc76aca9d4e2629877b12781490020c6f85a2"}]}